rayson/__init__.py
rayson/module.py
rayson-0.0.4.dist-info/LICENSE.txt
rayson-0.0.4.dist-info/METADATA
rayson-0.0.4.dist-info/WHEEL
rayson-0.0.4.dist-info/top_level.txt
rayson-0.0.4.dist-info/RECORD
