Metadata-Version: 2.1
Name: rayson
Version: 0.0.4
Summary: Generate scripts for JSON instantly for faster development and testing
Home-page: https://github.com/ray837/JSONQL
Author: Rayid Ahmed
Author-email: rayidahmed@gmail.com
Classifier: Programming Language :: Python :: 3
Classifier: License :: OSI Approved :: MIT License
Classifier: Operating System :: OS Independent
Requires-Python: >=3.6
License-File: LICENSE.txt
